ultrade/__init__.py
ultrade/constants.py
ultrade/sdk_client.py
ultrade/socket_client.py
ultrade/socket_options.py
ultrade/types.py
ultrade/signers/__init__.py
ultrade/signers/algorand.py
ultrade/signers/ethereum.py
ultrade/signers/main.py
ultrade/signers/private_key.py
ultrade/utils/__init__.py
ultrade/utils/algod_service.py
ultrade/utils/decode.py
ultrade/utils/encode.py
ultrade/utils/utils.py
ultrade_sdk-0.3.19.data/data/requirements.txt
ultrade_sdk-0.3.19.dist-info/METADATA
ultrade_sdk-0.3.19.dist-info/WHEEL
ultrade_sdk-0.3.19.dist-info/top_level.txt
ultrade_sdk-0.3.19.dist-info/RECORD
