Metadata-Version: 2.4
Name: ultrade-sdk
Version: 0.3.19
Summary: This SDK provides interface that helps making trading operations within the Ultrade network easier
Home-page: https://github.com/ultrade-org/ultrade-python-sdk
Author: Ultrade
License: MIT
Requires-Python: >=3.10
Requires-Dist: py-algorand-sdk>=2.0.0
Requires-Dist: python-socketio>=5.0.0
Requires-Dist: asyncio>=3.4.3
Requires-Dist: aiohttp>=3.7.4
Requires-Dist: bip-utils>=2.0.0
Requires-Dist: web3==6.12.0
Requires-Dist: base58>=2.1.0
Requires-Dist: pytest_asyncio>=0.23.5
Requires-Dist: solana>=0.35.1
Provides-Extra: dev
Requires-Dist: pytest>=7.0; extra == "dev"
Requires-Dist: twine>=4.0.2; extra == "dev"
Dynamic: author
Dynamic: description
Dynamic: description-content-type
Dynamic: home-page
Dynamic: license
Dynamic: provides-extra
Dynamic: requires-dist
Dynamic: requires-python
Dynamic: summary
